{"generated_at": "2026-07-20T03:14:34+00:00", "source": "binance-native", "onchain_checked": 25, "regime": {"verdict": "様子見", "btc_ma50_dev": 0.61, "btc_chg24": 0.22, "ctx": 5}, "rows": [{"sym": "ZROUSDT", "heat": 52, "price": 0.7716, "chg24": -5.1, "chg1": -0.3, "funding": -0.0005, "oitr": -0.1, "oidrop": 2.4, "taker": 0.72, "toplong": 79.5, "pump24": 0.2, "neartop": 6.4, "fcool": false, "cex_usd": 19840556, "flow_pct": 3.2, "flow_usd": 615143, "deposit_ramp": true, "cex_withdraw": false, "chain": "ethereum", "top10": 39.16, "top10_chg": 0.0, "conc_high": false, "whale_distrib": false, "rv_lv": 0, "reversal": false, "wings": false, "berserk": false, "beast": false, "beast30": false, "awakened": false}, {"sym": "TLMUSDT", "heat": 52, "price": 0.002082, "chg24": 34.6, "chg1": -3.6, "funding": -0.0589, "oitr": 1.3, "oidrop": 17.7, "taker": 1.15, "toplong": 51.7, "pump24": 36.7, "neartop": 24.2, "fcool": true, "top10": 76.5, "top10_chg": -3.05, "conc_high": true, "whale_distrib": true, "rv_lv": 0, "reversal": false, "wings": false, "berserk": false, "beast": false, "beast30": false, "awakened": false}, {"sym": "SIRENUSDT", "heat": 48, "price": 0.03039, "chg24": 5.1, "chg1": 0.2, "funding": 0.1056, "oitr": 0.7, "oidrop": 0.0, "taker": 0.81, "toplong": 58.9, "pump24": 18.5, "neartop": 3.6, "fcool": false, "cex_usd": 1, "flow_pct": 0.0, "flow_usd": 0, "deposit_ramp": false, "cex_withdraw": false, "chain": "binance-smart-chain", "rv_lv": 0, "reversal": false, "wings": false, "berserk": false, "beast": false, "beast30": false, "awakened": false}, {"sym": "YGGUSDT", "heat": 46, "price": 0.01868, "chg24": -11.3, "chg1": 0.2, "funding": 0.0026, "oitr": 1.0, "oidrop": 6.4, "taker": 0.61, "toplong": 69.2, "pump24": 3.8, "neartop": 11.9, "fcool": false, "cex_usd": 4318315, "flow_pct": 0.9, "flow_usd": 39651, "deposit_ramp": false, "cex_withdraw": false, "chain": "ethereum", "top10": 73.86, "top10_chg": 0.0, "conc_high": true, "whale_distrib": false, "rv_lv": 0, "reversal": false, "wings": false, "berserk": false, "beast": false, "beast30": false, "awakened": false}, {"sym": "PENDLEUSDT", "heat": 46, "price": 1.5706, "chg24": 1.8, "chg1": -0.1, "funding": 0.01, "oitr": 0.0, "oidrop": 0.1, "taker": 0.69, "toplong": 69.7, "pump24": 4.0, "neartop": 1.3, "fcool": false, "cex_usd": 41283140, "flow_pct": 0.0, "flow_usd": 6123, "deposit_ramp": false, "cex_withdraw": false, "chain": "ethereum", "top10": 69.95, "top10_chg": 0.0, "conc_high": true, "whale_distrib": false, "rv_lv": 0, "reversal": false, "wings": false, "berserk": false, "beast": false, "beast30": false, "awakened": false}, {"sym": "VANRYUSDT", "heat": 46, "price": 0.005285, "chg24": 3.3, "chg1": -0.5, "funding": -0.0841, "oitr": -1.6, "oidrop": 7.8, "taker": 0.76, "toplong": 57.8, "pump24": 5.9, "neartop": 11.3, "fcool": true, "top10": 69.63, "top10_chg": -1.12, "conc_high": true, "whale_distrib": true, "rv_lv": 0, "reversal": false, "wings": false, "berserk": false, "beast": false, "beast30": false, "awakened": false}, {"sym": "GUSDT", "heat": 40, "price": 0.003394, "chg24": -2.0, "chg1": -0.1, "funding": -0.1252, "oitr": -2.3, "oidrop": 41.6, "taker": 0.57, "toplong": 60.3, "pump24": 1.4, "neartop": 30.0, "fcool": true, "cex_usd": 3372269, "flow_pct": -9.8, "flow_usd": -365383, "deposit_ramp": false, "cex_withdraw": true, "chain": "ethereum", "top10": 85.99, "top10_chg": -0.13, "conc_high": true, "whale_distrib": false, "rv_lv": 0, "reversal": false, "wings": false, "berserk": false, "beast": false, "beast30": false, "awakened": false}, {"sym": "LITUSDT", "heat": 40, "price": 2.2186, "chg24": -0.7, "chg1": -0.1, "funding": 0.005, "oitr": -0.4, "oidrop": 0.5, "taker": 0.8, "toplong": 69.6, "pump24": 1.9, "neartop": 2.6, "fcool": false, "cex_usd": 25725829, "flow_pct": 1.2, "flow_usd": 311743, "deposit_ramp": false, "cex_withdraw": false, "chain": "ethereum", "top10": 66.59, "top10_chg": -0.02, "conc_high": true, "whale_distrib": false, "rv_lv": 0, "reversal": false, "wings": false, "berserk": false, "beast": false, "beast30": false, "awakened": false}, {"sym": "ONUSDT", "heat": 40, "price": 0.10867, "chg24": 8.8, "chg1": -2.0, "funding": 0.005, "oitr": -1.7, "oidrop": 13.8, "taker": 0.71, "toplong": 63.8, "pump24": 8.3, "neartop": 16.3, "fcool": false, "cex_usd": 1064780, "flow_pct": 0.0, "flow_usd": 0, "deposit_ramp": false, "cex_withdraw": false, "chain": "ethereum", "top10": 91.14, "top10_chg": 0.0, "conc_high": true, "whale_distrib": false, "rv_lv": 0, "reversal": false, "wings": false, "berserk": false, "beast": false, "beast30": false, "awakened": false}, {"sym": "ROBOUSDT", "heat": 40, "price": 0.0118, "chg24": 10.1, "chg1": -0.8, "funding": 0.005, "oitr": -0.3, "oidrop": 1.8, "taker": 0.81, "toplong": 72.3, "pump24": 11.4, "neartop": 4.1, "fcool": false, "cex_usd": 6181667, "flow_pct": 0.5, "flow_usd": 31879, "deposit_ramp": false, "cex_withdraw": false, "chain": "ethereum", "top10": 93.62, "top10_chg": 0.11, "conc_high": true, "whale_distrib": false, "rv_lv": 0, "reversal": false, "wings": false, "berserk": false, "beast": false, "beast30": false, "awakened": false}, {"sym": "SKYUSDT", "heat": 40, "price": 0.06148, "chg24": -0.1, "chg1": 0.2, "funding": 0.005, "oitr": -0.3, "oidrop": 3.5, "taker": 0.46, "toplong": 61.5, "pump24": 3.1, "neartop": 1.5, "fcool": false, "cex_usd": 37037744, "flow_pct": -0.0, "flow_usd": -18087, "deposit_ramp": false, "cex_withdraw": false, "chain": "ethereum", "top10": 90.43, "top10_chg": 0.02, "conc_high": true, "whale_distrib": false, "rv_lv": 0, "reversal": false, "wings": false, "berserk": false, "beast": false, "beast30": false, "awakened": false}, {"sym": "PROMUSDT", "heat": 38, "price": 1.603, "chg24": 19.1, "chg1": -3.0, "funding": -0.0078, "oitr": -4.4, "oidrop": 6.6, "taker": 0.87, "toplong": 57.8, "pump24": 20.1, "neartop": 10.2, "fcool": false, "cex_usd": 5935046, "flow_pct": 1.0, "flow_usd": 61273, "deposit_ramp": false, "cex_withdraw": false, "chain": "ethereum", "top10": 71.26, "top10_chg": 0.0, "conc_high": true, "whale_distrib": false, "rv_lv": 0, "reversal": false, "wings": false, "berserk": false, "beast": false, "beast30": false, "awakened": false}, {"sym": "AVAAIUSDT", "heat": 36, "price": 0.011108, "chg24": 36.1, "chg1": 1.6, "funding": 0.038, "oitr": 0.7, "oidrop": 2.6, "taker": 0.95, "toplong": 58.7, "pump24": 49.5, "neartop": 2.5, "fcool": true, "rv_lv": 1, "reversal": false, "wings": false, "berserk": false, "beast": false, "beast30": false, "awakened": false}, {"sym": "ZEREBROUSDT", "heat": 36, "price": 0.046314, "chg24": 36.6, "chg1": -0.5, "funding": 0.064, "oitr": 0.1, "oidrop": 0.0, "taker": 1.01, "toplong": 51.5, "pump24": 43.2, "neartop": 7.4, "fcool": false, "rv_lv": 0, "reversal": false, "wings": false, "berserk": false, "beast": false, "beast30": false, "awakened": false}, {"sym": "INJUSDT", "heat": 34, "price": 5.141, "chg24": 0.8, "chg1": 0.0, "funding": -0.0059, "oitr": -0.1, "oidrop": 2.1, "taker": 0.8, "toplong": 59.7, "pump24": 2.3, "neartop": 1.0, "fcool": false, "cex_usd": 790528, "flow_pct": 1.1, "flow_usd": 8375, "deposit_ramp": false, "cex_withdraw": false, "chain": "ethereum", "top10": 92.35, "top10_chg": 0.01, "conc_high": true, "whale_distrib": false, "rv_lv": 0, "reversal": false, "wings": false, "berserk": false, "beast": false, "beast30": false, "awakened": false}, {"sym": "BTWUSDT", "heat": 34, "price": 0.06591, "chg24": 1.3, "chg1": -1.7, "funding": 0.0269, "oitr": -1.0, "oidrop": 3.1, "taker": 0.84, "toplong": 64.3, "pump24": 6.8, "neartop": 9.7, "fcool": false, "cex_usd": 0, "flow_pct": null, "flow_usd": null, "deposit_ramp": false, "cex_withdraw": false, "chain": "ethereum", "top10": 100.0, "top10_chg": 0.0, "conc_high": true, "whale_distrib": false, "rv_lv": 0, "reversal": false, "wings": false, "berserk": false, "beast": false, "beast30": false, "awakened": false}, {"sym": "PHAUSDT", "heat": 34, "price": 0.02313, "chg24": -4.9, "chg1": 0.3, "funding": -0.0029, "oitr": 0.2, "oidrop": 18.1, "taker": 0.75, "toplong": 59.1, "pump24": 1.1, "neartop": 5.7, "fcool": false, "cex_usd": 6810960, "flow_pct": -0.2, "flow_usd": -16514, "deposit_ramp": false, "cex_withdraw": false, "chain": "ethereum", "top10": 65.98, "top10_chg": -0.18, "conc_high": true, "whale_distrib": false, "rv_lv": 0, "reversal": false, "wings": false, "berserk": false, "beast": false, "beast30": false, "awakened": false}, {"sym": "DOGEUSDT", "heat": 32, "price": 0.07273, "chg24": 0.3, "chg1": 0.1, "funding": 0.0026, "oitr": -0.8, "oidrop": 0.9, "taker": 0.71, "toplong": 70.7, "pump24": 1.6, "neartop": 0.5, "fcool": false, "rv_lv": 0, "reversal": false, "wings": false, "berserk": false, "beast": false, "beast30": false, "awakened": false}, {"sym": "PAXGUSDT", "heat": 32, "price": 4016.6, "chg24": 0.2, "chg1": -0.0, "funding": 0.0036, "oitr": -0.5, "oidrop": 0.5, "taker": 0.54, "toplong": 73.1, "pump24": 0.9, "neartop": 0.2, "fcool": false, "cex_usd": 406171407, "flow_pct": 0.1, "flow_usd": 277524, "deposit_ramp": false, "cex_withdraw": false, "chain": "ethereum", "top10": 33.34, "top10_chg": -0.1, "conc_high": false, "whale_distrib": false, "rv_lv": 0, "reversal": false, "wings": false, "berserk": false, "beast": false, "beast30": false, "awakened": false}, {"sym": "ASTERUSDT", "heat": 32, "price": 0.6207, "chg24": -0.3, "chg1": 0.1, "funding": 0.0028, "oitr": 0.1, "oidrop": 0.7, "taker": 0.61, "toplong": 69.6, "pump24": 1.0, "neartop": 0.8, "fcool": false, "cex_usd": 43247959, "flow_pct": -0.4, "flow_usd": -161212, "deposit_ramp": false, "cex_withdraw": false, "chain": "binance-smart-chain", "rv_lv": 0, "reversal": false, "wings": false, "berserk": false, "beast": false, "beast30": false, "awakened": false}, {"sym": "TUSDT", "heat": 32, "price": 0.003826, "chg24": -2.0, "chg1": 0.1, "funding": -0.0264, "oitr": -1.3, "oidrop": 8.1, "taker": 0.69, "toplong": 54.8, "pump24": 0.8, "neartop": 7.8, "fcool": false, "top10": 73.37, "top10_chg": -0.47, "conc_high": true, "whale_distrib": false, "rv_lv": 0, "reversal": false, "wings": false, "berserk": false, "beast": false, "beast30": false, "awakened": false}, {"sym": "ZBTUSDT", "heat": 28, "price": 0.09502, "chg24": -10.7, "chg1": -1.2, "funding": 0.005, "oitr": 0.1, "oidrop": 3.7, "taker": 1.24, "toplong": 68.0, "pump24": 3.2, "neartop": 11.3, "fcool": false, "top10": 98.39, "top10_chg": -0.11, "conc_high": true, "whale_distrib": false, "rv_lv": 0, "reversal": false, "wings": false, "berserk": false, "beast": false, "beast30": false, "awakened": false}, {"sym": "LUMIAUSDT", "heat": 28, "price": 0.0753, "chg24": 10.4, "chg1": 0.6, "funding": 0.005, "oitr": 0.0, "oidrop": 8.7, "taker": 1.34, "toplong": 75.3, "pump24": 13.6, "neartop": 0.9, "fcool": false, "top10": 96.06, "top10_chg": 0.01, "conc_high": true, "whale_distrib": false, "rv_lv": 0, "reversal": false, "wings": false, "berserk": false, "beast": false, "beast30": false, "awakened": false}, {"sym": "ETHFIUSDT", "heat": 28, "price": 0.4496, "chg24": -1.5, "chg1": 0.4, "funding": 0.005, "oitr": -0.1, "oidrop": 2.4, "taker": 1.1, "toplong": 72.1, "pump24": 1.6, "neartop": 2.0, "fcool": false, "top10": 64.21, "top10_chg": 0.01, "conc_high": true, "whale_distrib": false, "rv_lv": 0, "reversal": false, "wings": false, "berserk": false, "beast": false, "beast30": false, "awakened": false}, {"sym": "KITEUSDT", "heat": 28, "price": 0.10965, "chg24": -2.8, "chg1": -0.1, "funding": 0.005, "oitr": -0.0, "oidrop": 1.2, "taker": 1.07, "toplong": 76.5, "pump24": 1.3, "neartop": 4.7, "fcool": false, "top10": 67.85, "top10_chg": 0.0, "conc_high": true, "whale_distrib": false, "rv_lv": 0, "reversal": false, "wings": false, "berserk": false, "beast": false, "beast30": false, "awakened": false}, {"sym": "RAVEUSDT", "heat": 28, "price": 0.2814, "chg24": -9.9, "chg1": 0.0, "funding": 0.005, "oitr": 0.3, "oidrop": 3.2, "taker": 1.01, "toplong": 66.6, "pump24": 2.3, "neartop": 11.0, "fcool": false, "top10": 97.62, "top10_chg": 0.0, "conc_high": true, "whale_distrib": false, "rv_lv": 0, "reversal": false, "wings": false, "berserk": false, "beast": false, "beast30": false, "awakened": false}, {"sym": "BSBUSDT", "heat": 28, "price": 0.13403, "chg24": -0.8, "chg1": -0.1, "funding": 0.0058, "oitr": -0.6, "oidrop": 3.1, "taker": 1.02, "toplong": 68.5, "pump24": 2.6, "neartop": 4.2, "fcool": false, "top10": 97.98, "top10_chg": 0.0, "conc_high": true, "whale_distrib": false, "rv_lv": 0, "reversal": false, "wings": false, "berserk": false, "beast": false, "beast30": false, "awakened": false}, {"sym": "BUSDT", "heat": 26, "price": 0.2317, "chg24": 37.2, "chg1": 2.1, "funding": 0.0217, "oitr": -0.3, "oidrop": 3.6, "taker": 1.09, "toplong": 61.2, "pump24": 40.1, "neartop": 10.7, "fcool": false, "cex_usd": 703, "flow_pct": 0.0, "flow_usd": 0, "deposit_ramp": false, "cex_withdraw": false, "chain": "binance-smart-chain", "rv_lv": 0, "reversal": false, "wings": false, "berserk": false, "beast": false, "beast30": false, "awakened": false}, {"sym": "KAITOUSDT", "heat": 26, "price": 0.9877, "chg24": 17.9, "chg1": 0.3, "funding": 0.005, "oitr": 0.9, "oidrop": 0.0, "taker": 1.25, "toplong": 73.6, "pump24": 18.1, "neartop": 0.8, "fcool": false, "rv_lv": 0, "reversal": false, "wings": false, "berserk": false, "beast": false, "beast30": false, "awakened": false}, {"sym": "TRADOORUSDT", "heat": 26, "price": 0.4886, "chg24": -17.5, "chg1": -0.6, "funding": 0.005, "oitr": -1.5, "oidrop": 21.5, "taker": 0.67, "toplong": 62.3, "pump24": 4.6, "neartop": 19.5, "fcool": false, "cex_usd": 0, "flow_pct": null, "flow_usd": null, "deposit_ramp": false, "cex_withdraw": false, "chain": "binance-smart-chain", "rv_lv": 0, "reversal": false, "wings": false, "berserk": false, "beast": false, "beast30": false, "awakened": false}, {"sym": "USELESSUSDT", "heat": 26, "price": 0.05645, "chg24": -9.2, "chg1": -0.6, "funding": 0.005, "oitr": 0.2, "oidrop": 0.1, "taker": 0.72, "toplong": 59.8, "pump24": 3.4, "neartop": 12.6, "fcool": false, "cex_usd": 0, "flow_pct": null, "flow_usd": null, "deposit_ramp": false, "cex_withdraw": false, "chain": "binance-smart-chain", "rv_lv": 0, "reversal": false, "wings": false, "berserk": false, "beast": false, "beast30": false, "awakened": false}, {"sym": "TIAUSDT", "heat": 26, "price": 0.363, "chg24": 0.7, "chg1": 0.1, "funding": 0.0031, "oitr": 0.7, "oidrop": 3.8, "taker": 0.67, "toplong": 63.7, "pump24": 3.7, "neartop": 0.9, "fcool": false, "rv_lv": 0, "reversal": false, "wings": false, "berserk": false, "beast": false, "beast30": false, "awakened": false}, {"sym": "FETUSDT", "heat": 26, "price": 0.1527, "chg24": -3.4, "chg1": -0.7, "funding": -0.0059, "oitr": -1.3, "oidrop": 1.8, "taker": 0.66, "toplong": 63.8, "pump24": 0.4, "neartop": 3.7, "fcool": false, "cex_usd": 7543961, "flow_pct": 0.4, "flow_usd": 28240, "deposit_ramp": false, "cex_withdraw": false, "chain": "ethereum", "top10": 47.08, "top10_chg": 0.0, "conc_high": false, "whale_distrib": false, "rv_lv": 0, "reversal": false, "wings": false, "berserk": false, "beast": false, "beast30": false, "awakened": false}, {"sym": "JELLYJELLYUSDT", "heat": 26, "price": 0.05616, "chg24": 4.6, "chg1": 0.2, "funding": 0.017, "oitr": -0.0, "oidrop": 0.2, "taker": 0.69, "toplong": 62.3, "pump24": 7.2, "neartop": 6.7, "fcool": false, "rv_lv": 0, "reversal": false, "wings": false, "berserk": false, "beast": false, "beast30": false, "awakened": false}, {"sym": "OPGUSDT", "heat": 26, "price": 0.104, "chg24": -1.0, "chg1": -0.3, "funding": 0.005, "oitr": 0.0, "oidrop": 4.8, "taker": 0.71, "toplong": 62.1, "pump24": 0.7, "neartop": 7.3, "fcool": false, "cex_usd": 590601, "flow_pct": -0.0, "flow_usd": 0, "deposit_ramp": false, "cex_withdraw": false, "chain": "binance-smart-chain", "rv_lv": 0, "reversal": false, "wings": false, "berserk": false, "beast": false, "beast30": false, "awakened": false}, {"sym": "BERAUSDT", "heat": 26, "price": 0.1902, "chg24": 4.4, "chg1": 0.1, "funding": -0.0021, "oitr": 0.9, "oidrop": 0.0, "taker": 0.81, "toplong": 65.6, "pump24": 6.8, "neartop": 1.4, "fcool": false, "rv_lv": 0, "reversal": false, "wings": false, "berserk": false, "beast": false, "beast30": false, "awakened": false}, {"sym": "DEXEUSDT", "heat": 26, "price": 34.48, "chg24": -2.2, "chg1": 0.3, "funding": 0.0042, "oitr": -0.0, "oidrop": 0.3, "taker": 0.86, "toplong": 52.0, "pump24": 7.5, "neartop": 3.0, "fcool": false, "top10": 98.65, "top10_chg": 0.0, "conc_high": true, "whale_distrib": false, "rv_lv": 0, "reversal": false, "wings": false, "berserk": false, "beast": false, "beast30": false, "awakened": false}, {"sym": "TOWNSUSDT", "heat": 26, "price": 0.002228, "chg24": 4.9, "chg1": -0.3, "funding": -0.1507, "oitr": -1.3, "oidrop": 13.8, "taker": 0.87, "toplong": 53.6, "pump24": 6.6, "neartop": 10.1, "fcool": true, "top10": 64.7, "top10_chg": 0.0, "conc_high": true, "whale_distrib": false, "rv_lv": 0, "reversal": false, "wings": false, "berserk": false, "beast": false, "beast30": false, "awakened": false}, {"sym": "IDOLUSDT", "heat": 24, "price": 0.01703, "chg24": -1.0, "chg1": 0.4, "funding": 0.0307, "oitr": 0.1, "oidrop": 34.5, "taker": 1.31, "toplong": 66.0, "pump24": 2.0, "neartop": 4.9, "fcool": false, "cex_usd": 0, "flow_pct": 0.0, "flow_usd": 0, "deposit_ramp": false, "cex_withdraw": false, "chain": "binance-smart-chain", "rv_lv": 0, "reversal": false, "wings": false, "berserk": false, "beast": false, "beast30": false, "awakened": false}, {"sym": "WLDUSDT", "heat": 22, "price": 0.3659, "chg24": -3.3, "chg1": -0.1, "funding": -0.0178, "oitr": -0.4, "oidrop": 4.0, "taker": 1.04, "toplong": 60.1, "pump24": 3.8, "neartop": 3.5, "fcool": true, "top10": 70.06, "top10_chg": -0.01, "conc_high": true, "whale_distrib": false, "rv_lv": 0, "reversal": false, "wings": false, "berserk": false, "beast": false, "beast30": false, "awakened": false}, {"sym": "ONDOUSDT", "heat": 22, "price": 0.3468, "chg24": 0.9, "chg1": -0.1, "funding": -0.0073, "oitr": 0.1, "oidrop": 2.9, "taker": 1.02, "toplong": 58.9, "pump24": 2.0, "neartop": 2.9, "fcool": false, "top10": 70.25, "top10_chg": 0.0, "conc_high": true, "whale_distrib": false, "rv_lv": 0, "reversal": false, "wings": false, "berserk": false, "beast": false, "beast30": false, "awakened": false}, {"sym": "REUSDT", "heat": 22, "price": 0.3814, "chg24": -7.8, "chg1": -0.6, "funding": -0.0524, "oitr": -0.2, "oidrop": 2.9, "taker": 0.93, "toplong": 60.8, "pump24": 0.9, "neartop": 12.4, "fcool": true, "top10": 97.58, "top10_chg": 0.03, "conc_high": true, "whale_distrib": false, "rv_lv": 0, "reversal": false, "wings": false, "berserk": false, "beast": false, "beast30": false, "awakened": false}, {"sym": "ALLOUSDT", "heat": 22, "price": 0.46115, "chg24": 3.8, "chg1": 0.2, "funding": 0.005, "oitr": -0.4, "oidrop": 4.6, "taker": 1.44, "toplong": 60.5, "pump24": 6.0, "neartop": 4.9, "fcool": false, "top10": 89.93, "top10_chg": 0.59, "conc_high": true, "whale_distrib": false, "rv_lv": 0, "reversal": false, "wings": false, "berserk": false, "beast": false, "beast30": false, "awakened": false}, {"sym": "ENAUSDT", "heat": 22, "price": 0.08071, "chg24": -0.1, "chg1": 0.3, "funding": 0.0011, "oitr": 0.1, "oidrop": 0.1, "taker": 0.95, "toplong": 62.9, "pump24": 2.3, "neartop": 0.5, "fcool": false, "top10": 61.59, "top10_chg": 0.0, "conc_high": true, "whale_distrib": false, "rv_lv": 0, "reversal": false, "wings": false, "berserk": false, "beast": false, "beast30": false, "awakened": false}, {"sym": "YBUSDT", "heat": 22, "price": 0.0906, "chg24": 10.2, "chg1": -0.7, "funding": 0.005, "oitr": -2.1, "oidrop": 6.7, "taker": 1.02, "toplong": 58.7, "pump24": 12.1, "neartop": 8.2, "fcool": false, "top10": 85.83, "top10_chg": -0.02, "conc_high": true, "whale_distrib": false, "rv_lv": 0, "reversal": false, "wings": false, "berserk": false, "beast": false, "beast30": false, "awakened": false}, {"sym": "CHZUSDT", "heat": 22, "price": 0.01483, "chg24": -4.9, "chg1": 0.1, "funding": -0.037, "oitr": -0.3, "oidrop": 1.7, "taker": 1.13, "toplong": 64.5, "pump24": 1.8, "neartop": 5.3, "fcool": false, "top10": 68.95, "top10_chg": 0.26, "conc_high": true, "whale_distrib": false, "rv_lv": 0, "reversal": false, "wings": false, "berserk": false, "beast": false, "beast30": false, "awakened": false}, {"sym": "UBUSDT", "heat": 22, "price": 0.08768, "chg24": -4.2, "chg1": 0.1, "funding": 0.005, "oitr": 0.1, "oidrop": 1.7, "taker": 1.28, "toplong": 59.8, "pump24": 3.0, "neartop": 5.3, "fcool": false, "top10": 99.88, "top10_chg": 0.0, "conc_high": true, "whale_distrib": false, "rv_lv": 0, "reversal": false, "wings": false, "berserk": false, "beast": false, "beast30": false, "awakened": false}, {"sym": "RIVERUSDT", "heat": 22, "price": 3.21, "chg24": -4.4, "chg1": -0.1, "funding": 0.005, "oitr": 0.4, "oidrop": 0.1, "taker": 1.04, "toplong": 60.0, "pump24": 1.7, "neartop": 4.7, "fcool": false, "top10": 99.96, "top10_chg": 0.0, "conc_high": true, "whale_distrib": false, "rv_lv": 0, "reversal": false, "wings": false, "berserk": false, "beast": false, "beast30": false, "awakened": false}, {"sym": "SOLUSDT", "heat": 20, "price": 76.85, "chg24": 1.1, "chg1": -0.1, "funding": 0.0037, "oitr": -0.2, "oidrop": 1.7, "taker": 0.77, "toplong": 62.3, "pump24": 2.0, "neartop": 0.7, "fcool": false, "rv_lv": 0, "reversal": false, "wings": false, "berserk": false, "beast": false, "beast30": false, "awakened": false}, {"sym": "XRPUSDT", "heat": 20, "price": 1.099, "chg24": 0.3, "chg1": -0.2, "funding": 0.0061, "oitr": -0.1, "oidrop": 0.1, "taker": 0.86, "toplong": 61.4, "pump24": 1.0, "neartop": 0.8, "fcool": false, "rv_lv": 0, "reversal": false, "wings": false, "berserk": false, "beast": false, "beast30": false, "awakened": false}, {"sym": "PUMPUSDT", "heat": 20, "price": 0.002029, "chg24": 23.2, "chg1": -0.3, "funding": 0.005, "oitr": 0.4, "oidrop": 0.2, "taker": 1.06, "toplong": 58.4, "pump24": 23.8, "neartop": 2.0, "fcool": false, "rv_lv": 0, "reversal": false, "wings": false, "berserk": false, "beast": false, "beast30": false, "awakened": false}, {"sym": "TAGUSDT", "heat": 20, "price": 0.001212, "chg24": 19.3, "chg1": 0.6, "funding": 0.0166, "oitr": 0.6, "oidrop": 1.8, "taker": 1.02, "toplong": 63.6, "pump24": 20.5, "neartop": 4.9, "fcool": false, "cex_usd": 0, "flow_pct": null, "flow_usd": null, "deposit_ramp": false, "cex_withdraw": false, "chain": "binance-smart-chain", "rv_lv": 0, "reversal": false, "wings": false, "berserk": false, "beast": false, "beast30": false, "awakened": false}, {"sym": "BASEDUSDT", "heat": 20, "price": 0.09146, "chg24": -1.0, "chg1": -0.1, "funding": 0.005, "oitr": 0.4, "oidrop": 4.3, "taker": 0.76, "toplong": 58.5, "pump24": 2.4, "neartop": 6.4, "fcool": false, "rv_lv": 0, "reversal": false, "wings": false, "berserk": false, "beast": false, "beast30": false, "awakened": false}, {"sym": "DODOXUSDT", "heat": 20, "price": 0.019743, "chg24": -6.1, "chg1": 0.4, "funding": -0.0053, "oitr": -0.3, "oidrop": 10.3, "taker": 0.77, "toplong": 62.9, "pump24": 0.6, "neartop": 8.5, "fcool": false, "rv_lv": 0, "reversal": false, "wings": false, "berserk": false, "beast": false, "beast30": false, "awakened": false}, {"sym": "SXTUSDT", "heat": 20, "price": 0.007126, "chg24": -4.8, "chg1": -0.5, "funding": 0.005, "oitr": 0.3, "oidrop": 3.5, "taker": 0.75, "toplong": 61.5, "pump24": 0.6, "neartop": 12.1, "fcool": false, "cex_usd": 4127841, "flow_pct": -0.2, "flow_usd": -10226, "deposit_ramp": false, "cex_withdraw": false, "chain": "ethereum", "top10": 41.5, "top10_chg": 0.0, "conc_high": false, "whale_distrib": false, "rv_lv": 0, "reversal": false, "wings": false, "berserk": false, "beast": false, "beast30": false, "awakened": false}, {"sym": "TACUSDT", "heat": 20, "price": 0.003427, "chg24": 1.3, "chg1": -0.1, "funding": 0.005, "oitr": -0.6, "oidrop": 5.8, "taker": 0.76, "toplong": 60.6, "pump24": 6.7, "neartop": 4.5, "fcool": false, "cex_usd": 0, "flow_pct": null, "flow_usd": null, "deposit_ramp": false, "cex_withdraw": false, "chain": "binance-smart-chain", "rv_lv": 0, "reversal": false, "wings": false, "berserk": false, "beast": false, "beast30": false, "awakened": false}, {"sym": "BANKUSDT", "heat": 18, "price": 0.24142, "chg24": 129.9, "chg1": -1.2, "funding": 0.005, "oitr": -2.5, "oidrop": 15.7, "taker": 1.27, "toplong": 55.6, "pump24": 133.8, "neartop": 9.9, "fcool": false, "cex_usd": 51138973, "flow_pct": -0.5, "flow_usd": -268384, "deposit_ramp": false, "cex_withdraw": false, "chain": "binance-smart-chain", "rv_lv": 0, "reversal": false, "wings": false, "berserk": false, "beast": false, "beast30": false, "awakened": false}, {"sym": "AKEUSDT", "heat": 18, "price": 0.0016402, "chg24": -10.2, "chg1": -3.6, "funding": 0.0553, "oitr": -2.9, "oidrop": 11.6, "taker": 0.93, "toplong": 54.5, "pump24": 14.6, "neartop": 34.8, "fcool": false, "rv_lv": 0, "reversal": false, "wings": false, "berserk": false, "beast": false, "beast30": false, "awakened": false}, {"sym": "ACEUSDT", "heat": 18, "price": 0.09648, "chg24": 53.6, "chg1": -0.3, "funding": -0.0914, "oitr": -4.8, "oidrop": 4.8, "taker": 0.94, "toplong": 53.9, "pump24": 56.4, "neartop": 8.9, "fcool": true, "rv_lv": 0, "reversal": false, "wings": false, "berserk": false, "beast": false, "beast30": false, "awakened": false}, {"sym": "USUSDT", "heat": 18, "price": 0.044806, "chg24": -3.1, "chg1": -1.4, "funding": 0.0397, "oitr": 0.4, "oidrop": 1.6, "taker": 1.23, "toplong": 60.7, "pump24": 19.9, "neartop": 9.8, "fcool": false, "rv_lv": 0, "reversal": false, "wings": false, "berserk": false, "beast": false, "beast30": false, "awakened": false}, {"sym": "ZORAUSDT", "heat": 18, "price": 0.006348, "chg24": 3.1, "chg1": 0.8, "funding": 0.005, "oitr": -1.6, "oidrop": 7.4, "taker": 0.73, "toplong": 49.6, "pump24": 4.2, "neartop": 6.8, "fcool": false, "rv_lv": 0, "reversal": false, "wings": false, "berserk": false, "beast": false, "beast30": false, "awakened": false}, {"sym": "TRUTHUSDT", "heat": 18, "price": 0.012786, "chg24": 1.8, "chg1": 0.8, "funding": 0.005, "oitr": -0.4, "oidrop": 1.7, "taker": 0.46, "toplong": 53.1, "pump24": 6.5, "neartop": 4.1, "fcool": false, "rv_lv": 0, "reversal": false, "wings": false, "berserk": false, "beast": false, "beast30": false, "awakened": false}, {"sym": "GUAUSDT", "heat": 18, "price": 0.05361, "chg24": -5.6, "chg1": 0.1, "funding": 0.0109, "oitr": -0.5, "oidrop": 6.5, "taker": 0.52, "toplong": 56.6, "pump24": 7.6, "neartop": 16.1, "fcool": false, "top10": 58.66, "top10_chg": 0.0, "conc_high": false, "whale_distrib": false, "rv_lv": 0, "reversal": false, "wings": false, "berserk": false, "beast": false, "beast30": false, "awakened": false}, {"sym": "HYPEUSDT", "heat": 14, "price": 60.481, "chg24": -0.2, "chg1": -0.1, "funding": 0.0031, "oitr": 0.1, "oidrop": 0.7, "taker": 0.95, "toplong": 67.2, "pump24": 0.7, "neartop": 1.9, "fcool": false, "rv_lv": 0, "reversal": false, "wings": false, "berserk": false, "beast": false, "beast30": false, "awakened": false}, {"sym": "NEARUSDT", "heat": 14, "price": 1.924, "chg24": 0.2, "chg1": -0.2, "funding": 0.01, "oitr": -0.3, "oidrop": 1.2, "taker": 0.99, "toplong": 68.7, "pump24": 1.5, "neartop": 1.0, "fcool": false, "rv_lv": 0, "reversal": false, "wings": false, "berserk": false, "beast": false, "beast30": false, "awakened": false}, {"sym": "SUIUSDT", "heat": 14, "price": 0.7512, "chg24": 1.1, "chg1": -0.2, "funding": 0.0088, "oitr": 0.1, "oidrop": 0.0, "taker": 0.92, "toplong": 69.7, "pump24": 1.5, "neartop": 1.0, "fcool": false, "rv_lv": 0, "reversal": false, "wings": false, "berserk": false, "beast": false, "beast30": false, "awakened": false}, {"sym": "LTCUSDT", "heat": 14, "price": 47.18, "chg24": 0.6, "chg1": -0.0, "funding": 0.01, "oitr": 0.1, "oidrop": 0.7, "taker": 0.97, "toplong": 66.9, "pump24": 1.1, "neartop": 1.4, "fcool": false, "rv_lv": 0, "reversal": false, "wings": false, "berserk": false, "beast": false, "beast30": false, "awakened": false}, {"sym": "FILUSDT", "heat": 14, "price": 0.7214, "chg24": -3.9, "chg1": -0.3, "funding": -0.0058, "oitr": -0.2, "oidrop": 0.2, "taker": 1.45, "toplong": 67.6, "pump24": 1.7, "neartop": 4.2, "fcool": false, "rv_lv": 0, "reversal": false, "wings": false, "berserk": false, "beast": false, "beast30": false, "awakened": false}, {"sym": "TAOUSDT", "heat": 14, "price": 197.38, "chg24": 0.5, "chg1": -0.2, "funding": 0.005, "oitr": 0.0, "oidrop": 1.1, "taker": 0.94, "toplong": 66.4, "pump24": 1.3, "neartop": 2.0, "fcool": false, "rv_lv": 0, "reversal": false, "wings": false, "berserk": false, "beast": false, "beast30": false, "awakened": false}, {"sym": "UNIUSDT", "heat": 14, "price": 3.487, "chg24": -1.7, "chg1": -0.1, "funding": 0.0027, "oitr": 0.1, "oidrop": 0.4, "taker": 1.05, "toplong": 65.4, "pump24": 0.8, "neartop": 2.4, "fcool": false, "top10": 51.7, "top10_chg": 0.0, "conc_high": false, "whale_distrib": false, "rv_lv": 0, "reversal": false, "wings": false, "berserk": false, "beast": false, "beast30": false, "awakened": false}, {"sym": "ETCUSDT", "heat": 14, "price": 6.896, "chg24": -1.8, "chg1": 0.5, "funding": -0.0147, "oitr": 1.1, "oidrop": 4.5, "taker": 1.03, "toplong": 70.4, "pump24": 1.4, "neartop": 1.9, "fcool": false, "rv_lv": 0, "reversal": false, "wings": false, "berserk": false, "beast": false, "beast30": false, "awakened": false}, {"sym": "XAUTUSDT", "heat": 14, "price": 4019.61, "chg24": 0.2, "chg1": -0.0, "funding": 0.005, "oitr": 0.2, "oidrop": 4.8, "taker": 1.95, "toplong": 79.7, "pump24": 0.9, "neartop": 0.2, "fcool": false, "top10": 56.31, "top10_chg": 0.0, "conc_high": false, "whale_distrib": false, "rv_lv": 0, "reversal": false, "wings": false, "berserk": false, "beast": false, "beast30": false, "awakened": false}, {"sym": "XPLUSDT", "heat": 14, "price": 0.08268, "chg24": 0.3, "chg1": -0.1, "funding": 0.005, "oitr": 0.3, "oidrop": 1.1, "taker": 1.19, "toplong": 72.1, "pump24": 4.3, "neartop": 1.0, "fcool": false, "rv_lv": 0, "reversal": false, "wings": false, "berserk": false, "beast": false, "beast30": false, "awakened": false}, {"sym": "ORDIUSDT", "heat": 14, "price": 3.636, "chg24": -0.7, "chg1": 0.8, "funding": 0.0035, "oitr": -0.3, "oidrop": 4.8, "taker": 1.09, "toplong": 74.1, "pump24": 6.3, "neartop": 1.6, "fcool": false, "rv_lv": 0, "reversal": false, "wings": false, "berserk": false, "beast": false, "beast30": false, "awakened": false}, {"sym": "LDOUSDT", "heat": 14, "price": 0.3528, "chg24": -2.9, "chg1": 0.0, "funding": 0.0047, "oitr": -0.4, "oidrop": 3.5, "taker": 1.0, "toplong": 66.9, "pump24": 1.1, "neartop": 3.6, "fcool": false, "top10": 49.78, "top10_chg": 0.03, "conc_high": false, "whale_distrib": false, "rv_lv": 0, "reversal": false, "wings": false, "berserk": false, "beast": false, "beast30": false, "awakened": false}, {"sym": "DASHUSDT", "heat": 14, "price": 34.25, "chg24": -0.5, "chg1": -0.1, "funding": 0.0099, "oitr": -0.2, "oidrop": 3.7, "taker": 1.05, "toplong": 86.0, "pump24": 1.7, "neartop": 2.1, "fcool": false, "rv_lv": 0, "reversal": false, "wings": false, "berserk": false, "beast": false, "beast30": false, "awakened": false}, {"sym": "APTUSDT", "heat": 14, "price": 0.5935, "chg24": -2.5, "chg1": -0.2, "funding": 0.01, "oitr": 0.1, "oidrop": 0.0, "taker": 1.18, "toplong": 75.4, "pump24": 0.8, "neartop": 2.5, "fcool": false, "rv_lv": 0, "reversal": false, "wings": false, "berserk": false, "beast": false, "beast30": false, "awakened": false}, {"sym": "JUPUSDT", "heat": 14, "price": 0.2013, "chg24": 3.3, "chg1": 1.0, "funding": 0.005, "oitr": -0.2, "oidrop": 0.2, "taker": 0.95, "toplong": 66.7, "pump24": 6.7, "neartop": 1.2, "fcool": false, "rv_lv": 0, "reversal": false, "wings": false, "berserk": false, "beast": false, "beast30": false, "awakened": false}, {"sym": "EIGENUSDT", "heat": 14, "price": 0.2341, "chg24": 1.7, "chg1": 0.1, "funding": 0.005, "oitr": -0.2, "oidrop": 3.1, "taker": 1.02, "toplong": 66.6, "pump24": 3.4, "neartop": 0.3, "fcool": false, "top10": 37.23, "top10_chg": 0.02, "conc_high": false, "whale_distrib": false, "rv_lv": 0, "reversal": false, "wings": false, "berserk": false, "beast": false, "beast30": false, "awakened": false}, {"sym": "OPNUSDT", "heat": 14, "price": 0.06179, "chg24": -3.7, "chg1": 0.4, "funding": 0.005, "oitr": 0.3, "oidrop": 0.0, "taker": 1.14, "toplong": 70.8, "pump24": 1.3, "neartop": 4.1, "fcool": false, "top10": 59.2, "top10_chg": 0.02, "conc_high": false, "whale_distrib": false, "rv_lv": 0, "reversal": false, "wings": false, "berserk": false, "beast": false, "beast30": false, "awakened": false}, {"sym": "PARTIUSDT", "heat": 14, "price": 0.02918, "chg24": 3.5, "chg1": -0.9, "funding": 0.005, "oitr": -0.8, "oidrop": 4.5, "taker": 1.08, "toplong": 70.0, "pump24": 7.1, "neartop": 7.0, "fcool": false, "rv_lv": 0, "reversal": false, "wings": false, "berserk": false, "beast": false, "beast30": false, "awakened": false}, {"sym": "ICPUSDT", "heat": 14, "price": 2.145, "chg24": -1.1, "chg1": 0.0, "funding": 0.0061, "oitr": 0.0, "oidrop": 1.8, "taker": 1.15, "toplong": 79.7, "pump24": 1.1, "neartop": 1.3, "fcool": false, "top10": 42.97, "top10_chg": 0.59, "conc_high": false, "whale_distrib": false, "rv_lv": 0, "reversal": false, "wings": false, "berserk": false, "beast": false, "beast30": false, "awakened": false}, {"sym": "ZILUSDT", "heat": 14, "price": 0.002604, "chg24": -7.8, "chg1": 0.3, "funding": 0.0016, "oitr": 1.5, "oidrop": 0.0, "taker": 1.1, "toplong": 65.5, "pump24": 2.0, "neartop": 8.0, "fcool": false, "rv_lv": 0, "reversal": false, "wings": false, "berserk": false, "beast": false, "beast30": false, "awakened": false}, {"sym": "AUSDT", "heat": 14, "price": 0.06742, "chg24": 2.5, "chg1": -0.4, "funding": 0.0005, "oitr": -0.6, "oidrop": 7.7, "taker": 1.47, "toplong": 79.1, "pump24": 4.7, "neartop": 3.6, "fcool": false, "rv_lv": 0, "reversal": false, "wings": false, "berserk": false, "beast": false, "beast30": false, "awakened": false}, {"sym": "BILLUSDT", "heat": 14, "price": 0.02485, "chg24": -7.0, "chg1": -0.9, "funding": -0.0136, "oitr": -0.3, "oidrop": 11.0, "taker": 0.98, "toplong": 52.0, "pump24": 5.0, "neartop": 11.2, "fcool": false, "top10": 94.41, "top10_chg": -0.01, "conc_high": true, "whale_distrib": false, "rv_lv": 0, "reversal": false, "wings": false, "berserk": false, "beast": false, "beast30": false, "awakened": false}, {"sym": "SYNUSDT", "heat": 14, "price": 0.2115, "chg24": -2.8, "chg1": -0.3, "funding": 0.005, "oitr": -0.2, "oidrop": 0.8, "taker": 1.06, "toplong": 54.3, "pump24": 4.1, "neartop": 6.6, "fcool": false, "top10": 69.14, "top10_chg": -0.15, "conc_high": true, "whale_distrib": false, "rv_lv": 0, "reversal": false, "wings": false, "berserk": false, "beast": false, "beast30": false, "awakened": false}, {"sym": "ATHUSDT", "heat": 14, "price": 0.004816, "chg24": 9.3, "chg1": 0.1, "funding": 0.005, "oitr": -0.3, "oidrop": 1.6, "taker": 2.36, "toplong": 48.8, "pump24": 10.3, "neartop": 0.9, "fcool": false, "top10": 81.3, "top10_chg": 0.08, "conc_high": true, "whale_distrib": false, "rv_lv": 0, "reversal": false, "wings": false, "berserk": false, "beast": false, "beast30": false, "awakened": false}, {"sym": "WLFIUSDT", "heat": 14, "price": 0.05706, "chg24": -0.6, "chg1": 0.0, "funding": 0.005, "oitr": 0.2, "oidrop": 0.1, "taker": 1.79, "toplong": 43.9, "pump24": 0.6, "neartop": 1.6, "fcool": false, "top10": 87.14, "top10_chg": 0.0, "conc_high": true, "whale_distrib": false, "rv_lv": 0, "reversal": false, "wings": false, "berserk": false, "beast": false, "beast30": false, "awakened": false}, {"sym": "SOLVUSDT", "heat": 14, "price": 0.00261, "chg24": 2.0, "chg1": 0.1, "funding": 0.005, "oitr": -1.1, "oidrop": 15.2, "taker": 1.09, "toplong": 56.5, "pump24": 2.4, "neartop": 21.6, "fcool": false, "top10": 94.59, "top10_chg": 0.0, "conc_high": true, "whale_distrib": false, "rv_lv": 0, "reversal": false, "wings": false, "berserk": false, "beast": false, "beast30": false, "awakened": false}, {"sym": "VIRTUALUSDT", "heat": 14, "price": 0.6128, "chg24": 0.1, "chg1": -0.0, "funding": -0.0075, "oitr": -0.0, "oidrop": 0.6, "taker": 1.08, "toplong": 51.9, "pump24": 2.5, "neartop": 1.3, "fcool": false, "top10": 90.34, "top10_chg": 0.0, "conc_high": true, "whale_distrib": false, "rv_lv": 0, "reversal": false, "wings": false, "berserk": false, "beast": false, "beast30": false, "awakened": false}, {"sym": "SPACEUSDT", "heat": 14, "price": 0.005841, "chg24": -1.6, "chg1": -0.2, "funding": 0.005, "oitr": -2.0, "oidrop": 6.4, "taker": 1.15, "toplong": 54.1, "pump24": 0.4, "neartop": 8.2, "fcool": false, "top10": 83.9, "top10_chg": -0.03, "conc_high": true, "whale_distrib": false, "rv_lv": 0, "reversal": false, "wings": false, "berserk": false, "beast": false, "beast30": false, "awakened": false}, {"sym": "VANAUSDT", "heat": 14, "price": 1.152, "chg24": 3.5, "chg1": -0.1, "funding": 0.005, "oitr": 3.6, "oidrop": 0.0, "taker": 1.59, "toplong": 56.5, "pump24": 3.9, "neartop": 8.9, "fcool": false, "top10": 84.65, "top10_chg": -0.97, "conc_high": true, "whale_distrib": false, "rv_lv": 0, "reversal": false, "wings": false, "berserk": false, "beast": false, "beast30": false, "awakened": false}, {"sym": "EDGEUSDT", "heat": 14, "price": 0.421, "chg24": -1.3, "chg1": 0.0, "funding": 0.005, "oitr": -0.8, "oidrop": 6.6, "taker": 1.41, "toplong": 55.2, "pump24": 5.2, "neartop": 2.5, "fcool": false, "top10": 79.86, "top10_chg": -0.01, "conc_high": true, "whale_distrib": false, "rv_lv": 0, "reversal": false, "wings": false, "berserk": false, "beast": false, "beast30": false, "awakened": false}, {"sym": "0GUSDT", "heat": 14, "price": 0.1715, "chg24": 2.8, "chg1": -0.2, "funding": -0.0006, "oitr": 0.7, "oidrop": 0.9, "taker": 1.09, "toplong": 56.2, "pump24": 3.1, "neartop": 5.6, "fcool": false, "top10": 79.57, "top10_chg": 0.0, "conc_high": true, "whale_distrib": false, "rv_lv": 0, "reversal": false, "wings": false, "berserk": false, "beast": false, "beast30": false, "awakened": false}, {"sym": "RENDERUSDT", "heat": 14, "price": 1.489, "chg24": 0.1, "chg1": 0.1, "funding": 0.0016, "oitr": -0.0, "oidrop": 2.7, "taker": 1.14, "toplong": 54.3, "pump24": 1.5, "neartop": 0.7, "fcool": false, "top10": 93.3, "top10_chg": 0.0, "conc_high": true, "whale_distrib": false, "rv_lv": 0, "reversal": false, "wings": false, "berserk": false, "beast": false, "beast30": false, "awakened": false}, {"sym": "GWEIUSDT", "heat": 14, "price": 0.0284, "chg24": -8.1, "chg1": 1.4, "funding": -0.1076, "oitr": 0.3, "oidrop": 0.8, "taker": 1.68, "toplong": 48.4, "pump24": 4.0, "neartop": 10.1, "fcool": true, "top10": 96.87, "top10_chg": 0.03, "conc_high": true, "whale_distrib": false, "rv_lv": 0, "reversal": false, "wings": false, "berserk": false, "beast": false, "beast30": false, "awakened": false}, {"sym": "ETHUSDT", "heat": 12, "price": 1877.5, "chg24": 0.5, "chg1": -0.0, "funding": 0.005, "oitr": 0.2, "oidrop": 1.7, "taker": 0.82, "toplong": 58.0, "pump24": 1.4, "neartop": 0.7, "fcool": false, "rv_lv": 0, "reversal": false, "wings": false, "berserk": false, "beast": false, "beast30": false, "awakened": false}, {"sym": "ZECUSDT", "heat": 12, "price": 537.82, "chg24": -3.7, "chg1": 0.0, "funding": 0.0034, "oitr": -0.1, "oidrop": 4.0, "taker": 0.83, "toplong": 45.6, "pump24": 0.4, "neartop": 5.3, "fcool": false, "rv_lv": 0, "reversal": false, "wings": false, "berserk": false, "beast": false, "beast30": false, "awakened": false}, {"sym": "XLMUSDT", "heat": 12, "price": 0.18726, "chg24": -0.1, "chg1": -0.2, "funding": 0.0091, "oitr": -0.1, "oidrop": 1.6, "taker": 0.89, "toplong": 51.3, "pump24": 0.8, "neartop": 2.5, "fcool": false, "rv_lv": 0, "reversal": false, "wings": false, "berserk": false, "beast": false, "beast30": false, "awakened": false}, {"sym": "PHAROSUSDT", "heat": 12, "price": 0.3376, "chg24": -7.4, "chg1": -0.4, "funding": -0.0273, "oitr": 0.7, "oidrop": 0.0, "taker": 0.8, "toplong": 53.0, "pump24": 0.4, "neartop": 9.8, "fcool": false, "rv_lv": 0, "reversal": false, "wings": false, "berserk": false, "beast": false, "beast30": false, "awakened": false}, {"sym": "CLOUSDT", "heat": 12, "price": 0.14674, "chg24": -3.4, "chg1": 0.7, "funding": 0.005, "oitr": -0.5, "oidrop": 4.1, "taker": 0.8, "toplong": 49.5, "pump24": 2.8, "neartop": 11.6, "fcool": false, "rv_lv": 0, "reversal": false, "wings": false, "berserk": false, "beast": false, "beast30": false, "awakened": false}, {"sym": "NEOUSDT", "heat": 12, "price": 2.019, "chg24": -1.1, "chg1": -0.0, "funding": -0.0577, "oitr": 0.2, "oidrop": 8.9, "taker": 0.8, "toplong": 48.0, "pump24": 0.3, "neartop": 3.7, "fcool": true, "rv_lv": 0, "reversal": false, "wings": false, "berserk": false, "beast": false, "beast30": false, "awakened": false}, {"sym": "ESPORTSUSDT", "heat": 10, "price": 0.02259, "chg24": -51.4, "chg1": 2.9, "funding": 0.0304, "oitr": -0.2, "oidrop": 1.3, "taker": 1.0, "toplong": 52.9, "pump24": 12.9, "neartop": 56.9, "fcool": false, "rv_lv": 0, "reversal": false, "wings": false, "berserk": false, "beast": false, "beast30": false, "awakened": false}, {"sym": "BTCUSDT", "heat": 8, "price": 64759.8, "chg24": 0.1, "chg1": -0.1, "funding": 0.0037, "oitr": 0.1, "oidrop": 1.0, "taker": 0.97, "toplong": 59.5, "pump24": 0.8, "neartop": 0.5, "fcool": false, "rv_lv": 0, "reversal": false, "wings": false, "berserk": false, "beast": false, "beast30": false, "awakened": false}, {"sym": "1000PEPEUSDT", "heat": 8, "price": 0.0028971, "chg24": 5.4, "chg1": -0.4, "funding": 0.01, "oitr": 1.1, "oidrop": 0.0, "taker": 1.26, "toplong": 63.7, "pump24": 5.6, "neartop": 1.5, "fcool": false, "rv_lv": 0, "reversal": false, "wings": false, "berserk": false, "beast": false, "beast30": false, "awakened": false}, {"sym": "BNBUSDT", "heat": 8, "price": 570.65, "chg24": -0.0, "chg1": -0.0, "funding": 0.0066, "oitr": 0.1, "oidrop": 0.9, "taker": 1.34, "toplong": 62.4, "pump24": 0.7, "neartop": 0.7, "fcool": false, "top10": 56.71, "top10_chg": 0.0, "conc_high": false, "whale_distrib": false, "rv_lv": 0, "reversal": false, "wings": false, "berserk": false, "beast": false, "beast30": false, "awakened": false}, {"sym": "LABUSDT", "heat": 8, "price": 0.1481, "chg24": -23.3, "chg1": -0.8, "funding": 0.0204, "oitr": -0.0, "oidrop": 0.0, "taker": 1.02, "toplong": 59.8, "pump24": 4.8, "neartop": 24.1, "fcool": false, "rv_lv": 0, "reversal": false, "wings": false, "berserk": false, "beast": false, "beast30": false, "awakened": false}, {"sym": "AVAXUSDT", "heat": 8, "price": 6.624, "chg24": 0.4, "chg1": 0.1, "funding": 0.0031, "oitr": 1.4, "oidrop": 3.7, "taker": 1.25, "toplong": 59.5, "pump24": 3.7, "neartop": 0.4, "fcool": false, "rv_lv": 0, "reversal": false, "wings": false, "berserk": false, "beast": false, "beast30": false, "awakened": false}, {"sym": "LINKUSDT", "heat": 8, "price": 8.453, "chg24": 1.2, "chg1": -0.2, "funding": 0.0094, "oitr": -0.1, "oidrop": 0.2, "taker": 0.93, "toplong": 61.4, "pump24": 2.1, "neartop": 0.9, "fcool": false, "top10": 32.69, "top10_chg": 0.0, "conc_high": false, "whale_distrib": false, "rv_lv": 0, "reversal": false, "wings": false, "berserk": false, "beast": false, "beast30": false, "awakened": false}, {"sym": "DOTUSDT", "heat": 8, "price": 0.814, "chg24": -2.5, "chg1": 0.1, "funding": 0.0034, "oitr": 0.2, "oidrop": 0.0, "taker": 0.98, "toplong": 63.2, "pump24": 1.1, "neartop": 3.2, "fcool": false, "rv_lv": 0, "reversal": false, "wings": false, "berserk": false, "beast": false, "beast30": false, "awakened": false}, {"sym": "AAVEUSDT", "heat": 8, "price": 89.57, "chg24": -0.9, "chg1": 0.0, "funding": 0.0044, "oitr": -0.6, "oidrop": 2.5, "taker": 1.03, "toplong": 63.6, "pump24": 1.2, "neartop": 1.5, "fcool": false, "top10": 41.68, "top10_chg": 0.0, "conc_high": false, "whale_distrib": false, "rv_lv": 0, "reversal": false, "wings": false, "berserk": false, "beast": false, "beast30": false, "awakened": false}, {"sym": "BULLAUSDT", "heat": 8, "price": 0.009099, "chg24": -18.7, "chg1": -1.2, "funding": 0.005, "oitr": -0.4, "oidrop": 9.7, "taker": 0.95, "toplong": 63.4, "pump24": 6.7, "neartop": 25.9, "fcool": false, "rv_lv": 0, "reversal": false, "wings": false, "berserk": false, "beast": false, "beast30": false, "awakened": false}, {"sym": "ARIAUSDT", "heat": 8, "price": 0.02536, "chg24": -7.8, "chg1": -0.2, "funding": 0.005, "oitr": -0.5, "oidrop": 19.1, "taker": 1.19, "toplong": 60.0, "pump24": 3.3, "neartop": 25.5, "fcool": false, "rv_lv": 0, "reversal": false, "wings": false, "berserk": false, "beast": false, "beast30": false, "awakened": false}, {"sym": "SKLUSDT", "heat": 8, "price": 0.004097, "chg24": 5.6, "chg1": 0.4, "funding": -0.1336, "oitr": -0.5, "oidrop": 3.9, "taker": 1.0, "toplong": 58.1, "pump24": 8.0, "neartop": 7.5, "fcool": true, "top10": 41.69, "top10_chg": -0.64, "conc_high": false, "whale_distrib": false, "rv_lv": 0, "reversal": false, "wings": false, "berserk": false, "beast": false, "beast30": false, "awakened": false}, {"sym": "JTOUSDT", "heat": 8, "price": 0.6092, "chg24": 11.1, "chg1": -0.5, "funding": 0.005, "oitr": 2.5, "oidrop": 0.0, "taker": 1.04, "toplong": 61.4, "pump24": 13.8, "neartop": 0.7, "fcool": false, "rv_lv": 0, "reversal": false, "wings": false, "berserk": false, "beast": false, "beast30": false, "awakened": false}, {"sym": "OPUSDT", "heat": 8, "price": 0.095, "chg24": -0.6, "chg1": 0.0, "funding": 0.01, "oitr": 0.3, "oidrop": 1.0, "taker": 1.28, "toplong": 62.3, "pump24": 2.3, "neartop": 0.9, "fcool": false, "rv_lv": 0, "reversal": false, "wings": false, "berserk": false, "beast": false, "beast30": false, "awakened": false}, {"sym": "HBARUSDT", "heat": 8, "price": 0.06606, "chg24": -1.3, "chg1": -0.2, "funding": -0.0142, "oitr": -0.0, "oidrop": 0.0, "taker": 1.17, "toplong": 64.6, "pump24": 0.4, "neartop": 1.9, "fcool": false, "rv_lv": 0, "reversal": false, "wings": false, "berserk": false, "beast": false, "beast30": false, "awakened": false}, {"sym": "VELVETUSDT", "heat": 8, "price": 0.5186, "chg24": 0.8, "chg1": 1.7, "funding": 0.005, "oitr": -0.0, "oidrop": 4.3, "taker": 1.17, "toplong": 62.8, "pump24": 10.3, "neartop": 2.5, "fcool": false, "rv_lv": 0, "reversal": false, "wings": false, "berserk": false, "beast": false, "beast30": false, "awakened": false}, {"sym": "BLESSUSDT", "heat": 8, "price": 0.009271, "chg24": 6.3, "chg1": -0.1, "funding": 0.0209, "oitr": 0.4, "oidrop": 0.9, "taker": 1.12, "toplong": 62.7, "pump24": 6.9, "neartop": 8.9, "fcool": false, "rv_lv": 0, "reversal": false, "wings": false, "berserk": false, "beast": false, "beast30": false, "awakened": false}, {"sym": "ATOMUSDT", "heat": 8, "price": 1.46, "chg24": -2.6, "chg1": 0.1, "funding": -0.0195, "oitr": -0.1, "oidrop": 0.6, "taker": 1.06, "toplong": 58.8, "pump24": 0.4, "neartop": 2.6, "fcool": false, "rv_lv": 0, "reversal": false, "wings": false, "berserk": false, "beast": false, "beast30": false, "awakened": false}, {"sym": "WIFUSDT", "heat": 8, "price": 0.1536, "chg24": 0.6, "chg1": -0.1, "funding": 0.005, "oitr": -0.4, "oidrop": 2.9, "taker": 1.15, "toplong": 64.0, "pump24": 2.4, "neartop": 1.2, "fcool": false, "rv_lv": 0, "reversal": false, "wings": false, "berserk": false, "beast": false, "beast30": false, "awakened": false}, {"sym": "MANTRAUSDT", "heat": 8, "price": 0.006376, "chg24": 1.7, "chg1": -0.4, "funding": -0.0223, "oitr": -0.3, "oidrop": 17.4, "taker": 1.21, "toplong": 62.5, "pump24": 2.5, "neartop": 8.0, "fcool": false, "rv_lv": 0, "reversal": false, "wings": false, "berserk": false, "beast": false, "beast30": false, "awakened": false}, {"sym": "BEATUSDT", "heat": 8, "price": 2.369, "chg24": -0.1, "chg1": 1.3, "funding": 0.0113, "oitr": 0.3, "oidrop": 0.9, "taker": 1.01, "toplong": 60.0, "pump24": 3.3, "neartop": 3.7, "fcool": false, "rv_lv": 0, "reversal": false, "wings": false, "berserk": false, "beast": false, "beast30": false, "awakened": false}, {"sym": "ALGOUSDT", "heat": 8, "price": 0.0824, "chg24": -0.4, "chg1": 0.0, "funding": 0.01, "oitr": 0.4, "oidrop": 1.7, "taker": 1.38, "toplong": 61.0, "pump24": 1.4, "neartop": 1.3, "fcool": false, "rv_lv": 0, "reversal": false, "wings": false, "berserk": false, "beast": false, "beast30": false, "awakened": false}, {"sym": "1000FLOKIUSDT", "heat": 8, "price": 0.02136, "chg24": 2.4, "chg1": 0.0, "funding": -0.0093, "oitr": -0.1, "oidrop": 4.2, "taker": 1.16, "toplong": 58.3, "pump24": 3.0, "neartop": 0.2, "fcool": false, "rv_lv": 0, "reversal": false, "wings": false, "berserk": false, "beast": false, "beast30": false, "awakened": false}, {"sym": "QTUMUSDT", "heat": 8, "price": 0.7122, "chg24": 2.5, "chg1": 0.3, "funding": -0.0046, "oitr": -0.1, "oidrop": 8.6, "taker": 0.91, "toplong": 59.0, "pump24": 3.1, "neartop": 3.3, "fcool": false, "rv_lv": 0, "reversal": false, "wings": false, "berserk": false, "beast": false, "beast30": false, "awakened": false}, {"sym": "ARXUSDT", "heat": 8, "price": 0.1408, "chg24": -7.0, "chg1": -0.8, "funding": 0.002, "oitr": -0.6, "oidrop": 5.3, "taker": 1.03, "toplong": 64.0, "pump24": 0.1, "neartop": 7.7, "fcool": false, "rv_lv": 0, "reversal": false, "wings": false, "berserk": false, "beast": false, "beast30": false, "awakened": false}, {"sym": "MAGMAUSDT", "heat": 8, "price": 0.29826, "chg24": -2.5, "chg1": -0.2, "funding": 0.005, "oitr": -0.2, "oidrop": 4.9, "taker": 1.12, "toplong": 59.4, "pump24": 4.3, "neartop": 6.6, "fcool": false, "rv_lv": 0, "reversal": false, "wings": false, "berserk": false, "beast": false, "beast30": false, "awakened": false}, {"sym": "BCHUSDT", "heat": 0, "price": 213.64, "chg24": -2.2, "chg1": -0.0, "funding": 0.0017, "oitr": 0.0, "oidrop": 0.0, "taker": 1.12, "toplong": 46.0, "pump24": 1.0, "neartop": 2.7, "fcool": false, "rv_lv": 0, "reversal": false, "wings": false, "berserk": false, "beast": false, "beast30": false, "awakened": false}, {"sym": "ADAUSDT", "heat": 0, "price": 0.1656, "chg24": -1.1, "chg1": -0.1, "funding": 0.0044, "oitr": -0.2, "oidrop": 0.9, "taker": 0.93, "toplong": 49.1, "pump24": 1.2, "neartop": 1.6, "fcool": false, "rv_lv": 0, "reversal": false, "wings": false, "berserk": false, "beast": false, "beast30": false, "awakened": false}, {"sym": "HOMEUSDT", "heat": 0, "price": 0.00772, "chg24": 5.3, "chg1": -1.4, "funding": -0.3783, "oitr": 1.5, "oidrop": 13.6, "taker": 1.04, "toplong": 57.5, "pump24": 6.6, "neartop": 11.4, "fcool": true, "rv_lv": 0, "reversal": false, "wings": false, "berserk": false, "beast": false, "beast30": false, "awakened": false}, {"sym": "1000XECUSDT", "heat": 0, "price": 0.008048, "chg24": -4.6, "chg1": 1.5, "funding": -0.0563, "oitr": -0.5, "oidrop": 23.5, "taker": 1.27, "toplong": 49.9, "pump24": 3.7, "neartop": 9.2, "fcool": true, "rv_lv": 0, "reversal": false, "wings": false, "berserk": false, "beast": false, "beast30": false, "awakened": false}, {"sym": "TRUMPUSDT", "heat": 0, "price": 1.584, "chg24": -3.7, "chg1": -0.4, "funding": -0.0158, "oitr": -0.4, "oidrop": 6.3, "taker": 1.09, "toplong": 57.8, "pump24": 2.9, "neartop": 5.1, "fcool": false, "rv_lv": 0, "reversal": false, "wings": false, "berserk": false, "beast": false, "beast30": false, "awakened": false}, {"sym": "1000BONKUSDT", "heat": 0, "price": 0.002789, "chg24": 0.8, "chg1": -0.1, "funding": 0.005, "oitr": -0.2, "oidrop": 6.0, "taker": 1.15, "toplong": 56.5, "pump24": 2.0, "neartop": 6.6, "fcool": false, "rv_lv": 0, "reversal": false, "wings": false, "berserk": false, "beast": false, "beast30": false, "awakened": false}, {"sym": "PENGUUSDT", "heat": 0, "price": 0.006201, "chg24": 1.1, "chg1": 0.0, "funding": 0.005, "oitr": 0.3, "oidrop": 4.3, "taker": 1.02, "toplong": 57.1, "pump24": 3.3, "neartop": 0.4, "fcool": false, "top10": 50.27, "top10_chg": 0.04, "conc_high": false, "whale_distrib": false, "rv_lv": 0, "reversal": false, "wings": false, "berserk": false, "beast": false, "beast30": false, "awakened": false}, {"sym": "TRXUSDT", "heat": 0, "price": 0.32635, "chg24": 0.2, "chg1": -0.0, "funding": 0.0015, "oitr": -0.1, "oidrop": 1.7, "taker": 0.94, "toplong": 44.5, "pump24": 0.4, "neartop": 0.4, "fcool": false, "rv_lv": 0, "reversal": false, "wings": false, "berserk": false, "beast": false, "beast30": false, "awakened": false}, {"sym": "ARBUSDT", "heat": 0, "price": 0.08838, "chg24": 0.3, "chg1": -0.1, "funding": 0.0017, "oitr": 0.0, "oidrop": 1.0, "taker": 1.31, "toplong": 57.4, "pump24": 0.9, "neartop": 2.1, "fcool": false, "top10": 54.03, "top10_chg": 0.86, "conc_high": false, "whale_distrib": false, "rv_lv": 0, "reversal": false, "wings": false, "berserk": false, "beast": false, "beast30": false, "awakened": false}, {"sym": "SLXUSDT", "heat": 0, "price": 0.10303, "chg24": -6.3, "chg1": -0.4, "funding": -0.0539, "oitr": 1.2, "oidrop": 3.0, "taker": 0.96, "toplong": 56.9, "pump24": 1.9, "neartop": 9.1, "fcool": true, "rv_lv": 0, "reversal": false, "wings": false, "berserk": false, "beast": false, "beast30": false, "awakened": false}, {"sym": "EVAAUSDT", "heat": 0, "price": 0.8099, "chg24": -1.3, "chg1": 3.5, "funding": 0.005, "oitr": -0.2, "oidrop": 9.0, "taker": 0.96, "toplong": 56.9, "pump24": 7.1, "neartop": 3.7, "fcool": false, "rv_lv": 0, "reversal": false, "wings": false, "berserk": false, "beast": false, "beast30": false, "awakened": false}, {"sym": "XMRUSDT", "heat": 0, "price": 334.93, "chg24": -0.7, "chg1": -0.1, "funding": 0.0168, "oitr": 0.1, "oidrop": 0.5, "taker": 0.99, "toplong": 40.0, "pump24": 1.2, "neartop": 1.6, "fcool": false, "rv_lv": 0, "reversal": false, "wings": false, "berserk": false, "beast": false, "beast30": false, "awakened": false}, {"sym": "1000SHIBUSDT", "heat": 0, "price": 0.00418, "chg24": 0.9, "chg1": -0.1, "funding": 0.0067, "oitr": -0.0, "oidrop": 0.7, "taker": 0.98, "toplong": 57.7, "pump24": 2.0, "neartop": 0.4, "fcool": false, "rv_lv": 0, "reversal": false, "wings": false, "berserk": false, "beast": false, "beast30": false, "awakened": false}, {"sym": "FARTCOINUSDT", "heat": 0, "price": 0.134, "chg24": -0.3, "chg1": -0.1, "funding": 0.005, "oitr": 0.3, "oidrop": 1.6, "taker": 1.23, "toplong": 54.0, "pump24": 3.0, "neartop": 1.4, "fcool": false, "rv_lv": 0, "reversal": false, "wings": false, "berserk": false, "beast": false, "beast30": false, "awakened": false}, {"sym": "VVVUSDT", "heat": 0, "price": 11.606, "chg24": -1.9, "chg1": -0.3, "funding": 0.005, "oitr": -0.2, "oidrop": 4.0, "taker": 1.22, "toplong": 41.6, "pump24": 2.1, "neartop": 3.5, "fcool": false, "rv_lv": 0, "reversal": false, "wings": false, "berserk": false, "beast": false, "beast30": false, "awakened": false}, {"sym": "GRAMUSDT", "heat": 0, "price": 1.457, "chg24": -0.3, "chg1": 0.0, "funding": -0.0073, "oitr": -0.3, "oidrop": 1.2, "taker": 1.77, "toplong": 50.5, "pump24": 2.7, "neartop": 1.0, "fcool": false, "top10": 29.38, "top10_chg": 0.01, "conc_high": false, "whale_distrib": false, "rv_lv": 0, "reversal": false, "wings": false, "berserk": false, "beast": false, "beast30": false, "awakened": false}, {"sym": "EGLDUSDT", "heat": 0, "price": 3.16, "chg24": -1.9, "chg1": -0.4, "funding": 0.01, "oitr": -0.4, "oidrop": 16.7, "taker": 1.32, "toplong": 55.9, "pump24": 1.0, "neartop": 8.1, "fcool": false, "rv_lv": 0, "reversal": false, "wings": false, "berserk": false, "beast": false, "beast30": false, "awakened": false}, {"sym": "GALAUSDT", "heat": 0, "price": 0.002012, "chg24": -1.7, "chg1": 0.0, "funding": 0.0027, "oitr": 0.1, "oidrop": 0.0, "taker": 1.24, "toplong": 53.8, "pump24": 1.0, "neartop": 4.8, "fcool": false, "top10": 43.4, "top10_chg": -0.05, "conc_high": false, "whale_distrib": false, "rv_lv": 0, "reversal": false, "wings": false, "berserk": false, "beast": false, "beast30": false, "awakened": false}, {"sym": "AEROUSDT", "heat": 0, "price": 0.4548, "chg24": -0.7, "chg1": -0.1, "funding": 0.0005, "oitr": -0.1, "oidrop": 2.4, "taker": 2.38, "toplong": 56.7, "pump24": 3.0, "neartop": 1.4, "fcool": false, "rv_lv": 0, "reversal": false, "wings": false, "berserk": false, "beast": false, "beast30": false, "awakened": false}, {"sym": "SUSHIUSDT", "heat": 0, "price": 0.1674, "chg24": 2.2, "chg1": -0.2, "funding": -0.0001, "oitr": 0.4, "oidrop": 10.2, "taker": 1.8, "toplong": 56.4, "pump24": 3.2, "neartop": 6.3, "fcool": false, "top10": 42.15, "top10_chg": 0.07, "conc_high": false, "whale_distrib": false, "rv_lv": 0, "reversal": false, "wings": false, "berserk": false, "beast": false, "beast30": false, "awakened": false}, {"sym": "CRVUSDT", "heat": 0, "price": 0.2111, "chg24": -0.8, "chg1": -0.2, "funding": 0.01, "oitr": 0.2, "oidrop": 0.6, "taker": 1.58, "toplong": 57.8, "pump24": 1.3, "neartop": 1.7, "fcool": false, "top10": 57.69, "top10_chg": -0.01, "conc_high": false, "whale_distrib": false, "rv_lv": 0, "reversal": false, "wings": false, "berserk": false, "beast": false, "beast30": false, "awakened": false}, {"sym": "JASMYUSDT", "heat": 0, "price": 0.004692, "chg24": -3.5, "chg1": 0.1, "funding": -0.0123, "oitr": 0.5, "oidrop": 11.3, "taker": 1.37, "toplong": 58.0, "pump24": 2.3, "neartop": 3.6, "fcool": false, "top10": 50.44, "top10_chg": 0.0, "conc_high": false, "whale_distrib": false, "rv_lv": 0, "reversal": false, "wings": false, "berserk": false, "beast": false, "beast30": false, "awakened": false}]}